bpsproxy/__init__.py
bpsproxy/__main__.py
bpsproxy/call.py
bpsproxy/commands.py
bpsproxy/config.py
bpsproxy/utils.py
bpsproxy-0.2.1.dist-info/LICENSE
bpsproxy-0.2.1.dist-info/METADATA
bpsproxy-0.2.1.dist-info/WHEEL
bpsproxy-0.2.1.dist-info/entry_points.txt
bpsproxy-0.2.1.dist-info/top_level.txt
bpsproxy-0.2.1.dist-info/RECORD
