Metadata-Version: 2.1
Name: bpsproxy
Version: 0.2.1
Summary: Blender Power Sequencer proxy generator tool
Home-page: https://github.com/GDquest/BPSProxy
Author: Răzvan C. Rădulescu
Author-email: razcore.art@gmail.com
License: GPLv3
Keywords: blender proxy vse sequence editor productivity
Platform: UNKNOWN
Classifier: Development Status :: 5 - Production/Stable
Classifier: Environment :: Console
Classifier: Intended Audience :: End Users/Desktop
Classifier: License :: OSI Approved :: GNU General Public License v3 (GPLv3)
Classifier: Natural Language :: English
Classifier: Programming Language :: Python :: 3.3
Classifier: Programming Language :: Python :: 3.4
Classifier: Programming Language :: Python :: 3.5
Classifier: Programming Language :: Python :: 3.6
Classifier: Programming Language :: Python :: 3.7
Classifier: Programming Language :: Python :: 3
Classifier: Topic :: Multimedia :: Video
Classifier: Topic :: Utilities
Requires-Dist: tqdm
